pydantic_bigstitcher/__about__.py
pydantic_bigstitcher/__init__.py
pydantic_bigstitcher/transform.py
pydantic_bigstitcher-0.0.10.dist-info/METADATA
pydantic_bigstitcher-0.0.10.dist-info/WHEEL
pydantic_bigstitcher-0.0.10.dist-info/licenses/LICENSE.txt
pydantic_bigstitcher-0.0.10.dist-info/RECORD
