Metadata-Version: 2.3
Name: pydantic-bigstitcher
Version: 0.0.10
Project-URL: Documentation, https://github.com/d-v-b/pydantic-bigstitcher#readme
Project-URL: Issues, https://github.com/d-v-b/pydantic-bigstitcher/issues
Project-URL: Source, https://github.com/d-v-b/pydantic-bigstitcher
Author-email: Davis Vann Bennett <davis.v.bennett@gmail.com>
License-Expression: MIT
License-File: LICENSE.txt
Classifier: Development Status :: 4 - Beta
Classifier: Programming Language :: Python
Classifier: Programming Language :: Python :: 3.10
Classifier: Programming Language :: Python :: 3.11
Classifier: Programming Language :: Python :: 3.12
Classifier: Programming Language :: Python :: Implementation :: CPython
Classifier: Programming Language :: Python :: Implementation :: PyPy
Requires-Python: >=3.10
Requires-Dist: numpy
Requires-Dist: pydantic-xml>=2.9.2
Provides-Extra: docs
Requires-Dist: mkdocs-material>=9.5.39; extra == 'docs'
Requires-Dist: mkdocstrings[python]>=0.26.1; extra == 'docs'
Provides-Extra: test
Requires-Dist: coverage[toml]>=6.5; extra == 'test'
Requires-Dist: deepdiff==8.0.1; extra == 'test'
Requires-Dist: pytest; extra == 'test'
Requires-Dist: xmldiff; extra == 'test'
Requires-Dist: xmltodict; extra == 'test'
